fx_crash_sig/__init__.py
fx_crash_sig/cmd_get_crash_sig.py
fx_crash_sig/crash_processor.py
fx_crash_sig/example.py
fx_crash_sig/sample_traces.py
fx_crash_sig/symbolicate.py
fx_crash_sig/utils.py
fx_crash_sig-1.0.3.dist-info/LICENSE
fx_crash_sig-1.0.3.dist-info/METADATA
fx_crash_sig-1.0.3.dist-info/WHEEL
fx_crash_sig-1.0.3.dist-info/entry_points.txt
fx_crash_sig-1.0.3.dist-info/top_level.txt
fx_crash_sig-1.0.3.dist-info/RECORD
