Metadata-Version: 2.1
Name: fx-crash-sig
Version: 1.0.3
Summary: DEPRECATED: Get crash signature from Firefox crash ping
License: MPLv2
Project-URL: Homepage, https://github.com/mozilla-services/fx-crash-sig/
Project-URL: Source, https://github.com/mozilla-services/fx-crash-sig/
Project-URL: Issues, https://github.com/mozilla-services/fx-crash-sig/issues
Classifier: Intended Audience :: Developers
Classifier: License :: OSI Approved :: Mozilla Public License 2.0 (MPL 2.0)
Classifier: Programming Language :: Python :: 3 :: Only
Classifier: Programming Language :: Python :: 3.8
Classifier: Programming Language :: Python :: 3.9
Classifier: Programming Language :: Python :: 3.10
Classifier: Programming Language :: Python :: 3.11
Classifier: Programming Language :: Python :: 3.12
Classifier: Development Status :: 2 - Pre-Alpha
Requires-Python: >=3.8
License-File: LICENSE
Requires-Dist: requests
Requires-Dist: siggen
Requires-Dist: importlib-metadata
Provides-Extra: dev
Requires-Dist: build ; extra == 'dev'
Requires-Dist: check-manifest ; extra == 'dev'
Requires-Dist: pytest ; extra == 'dev'
Requires-Dist: ruff ; extra == 'dev'
Requires-Dist: tox ; extra == 'dev'
Requires-Dist: tox-gh-actions ; extra == 'dev'
Requires-Dist: twine ; extra == 'dev'
Requires-Dist: wheel ; extra == 'dev'
